Metadata-Version: 2.4
Name: llama-index-packs-neo4j-query-engine
Version: 0.5.1
Summary: llama-index packs neo4j_query_engine integration
Author-email: Your Name <you@example.com>
Maintainer: wenqiglantz
License-Expression: MIT
License-File: LICENSE
Keywords: knowledge graph,neo4j,query engine
Requires-Python: <4.0,>=3.9
Requires-Dist: llama-index-core<0.15,>=0.13.0
Requires-Dist: llama-index-graph-stores-neo4j<0.6,>=0.5.0
Requires-Dist: llama-index-llms-openai<0.6,>=0.5.0
Requires-Dist: neo4j<6,>=5.16.0
